python_redis_factory/__init__.py
python_redis_factory/config.py
python_redis_factory/interfaces.py
python_redis_factory/py.typed
python_redis_factory/simple_api.py
python_redis_factory/uri_parser.py
python_redis_factory/clients/__init__.py
python_redis_factory/clients/cluster.py
python_redis_factory/clients/sentinel.py
python_redis_factory/clients/standalone.py
python_redis_factory-0.2.0.dist-info/METADATA
python_redis_factory-0.2.0.dist-info/WHEEL
python_redis_factory-0.2.0.dist-info/RECORD
