Metadata-Version: 2.4
Name: python-redis-factory
Version: 0.2.0
Summary: A universal Redis client factory for Python—just pass a single connection string (supporting standalone, Sentinel, or Cluster modes) and get back a ready-to-use redis.Redis instance.
Project-URL: Homepage, https://github.com/smirnoffmg/python-redis-factory
Project-URL: Documentation, https://github.com/smirnoffmg/python-redis-factory#readme
Project-URL: Repository, https://github.com/smirnoffmg/python-redis-factory
Project-URL: Bug Tracker, https://github.com/smirnoffmg/python-redis-factory/issues
Project-URL: Changelog, https://github.com/smirnoffmg/python-redis-factory/blob/main/CHANGELOG.md
Author-email: Maksim Smirnov <smirnoffmg@gmail.com>
Maintainer-email: Maksim Smirnov <smirnoffmg@gmail.com>
License: MIT
Keywords: async,client,cluster,connection,factory,redis,sentinel
Classifier: Development Status :: 4 - Beta
Classifier: Intended Audience :: Developers
Classifier: License :: OSI Approved :: MIT License
Classifier: Operating System :: OS Independent
Classifier: Programming Language :: Python :: 3
Classifier: Programming Language :: Python :: 3.12
Classifier: Programming Language :: Python :: 3.13
Classifier: Topic :: Database
Classifier: Topic :: Software Development :: Libraries :: Python Modules
Classifier: Topic :: System :: Distributed Computing
Classifier: Typing :: Typed
Requires-Python: >=3.12
Requires-Dist: redis>=6.2.0
